z4d_certified_devices/__init__.py
z4d_certified_devices/version.py
z4d_certified_devices/Certified/README.md
z4d_certified_devices/Certified/Adeo/LDSENK01F.json
z4d_certified_devices/Certified/Adeo/LDSENK02F.json
z4d_certified_devices/Certified/Adeo/LDSENK08.json
z4d_certified_devices/Certified/Adeo/LDSENK10.json
z4d_certified_devices/Certified/Adeo/LXEK-1.json
z4d_certified_devices/Certified/Adeo/LXEK-2.json
z4d_certified_devices/Certified/Adeo/LXEK-7.json
z4d_certified_devices/Certified/Adeo/SIN-4-1-20_LEX.json
z4d_certified_devices/Certified/Adeo/SIN-4-FP-21_EQU.json
z4d_certified_devices/Certified/Adeo/SIN-4-RS-20_LEX.json
z4d_certified_devices/Certified/Adeo/ZBEK-13.json
z4d_certified_devices/Certified/Adeo/ZBEK-14.json
z4d_certified_devices/Certified/Adeo/ZBEK-3.json
z4d_certified_devices/Certified/Aeotec/aeotec-button.json
z4d_certified_devices/Certified/Aeotec/aeotec-water.json
z4d_certified_devices/Certified/Airzone/Aidoo Zigbee.json
z4d_certified_devices/Certified/Aotec/WG001-Z01.json
z4d_certified_devices/Certified/Awox/EGLO_ZM_RGB_TW.json
z4d_certified_devices/Certified/Awox/TLSR82xx.json
z4d_certified_devices/Certified/Bitron/90201021A.json
z4d_certified_devices/Certified/Bitron/90201021B.json
z4d_certified_devices/Certified/Bitron/90201022.json
z4d_certified_devices/Certified/Bitron/90201024.json
z4d_certified_devices/Certified/Bitron/AV201021B.json
z4d_certified_devices/Certified/Bitron/AV201024A.json
z4d_certified_devices/Certified/Bitron/AV201029A.json
z4d_certified_devices/Certified/CLEODE/ZHUM.json
z4d_certified_devices/Certified/CLEODE/ZMOVE.json
z4d_certified_devices/Certified/CLEODE/ZPLUG.json
z4d_certified_devices/Certified/Candeo/Candeo Zigbee Dimmer.json
z4d_certified_devices/Certified/Candeo/HK-DIM-A.json
z4d_certified_devices/Certified/Casa.ia/CAC221.json
z4d_certified_devices/Certified/Casa.ia/CCB432.json
z4d_certified_devices/Certified/Casa.ia/CDWS312.json
z4d_certified_devices/Certified/Casa.ia/CKF204.json
z4d_certified_devices-7.523.dist-info/licenses/LICENSE.txt
z4d_certified_devices-7.523.dist-info/METADATA
z4d_certified_devices-7.523.dist-info/WHEEL
z4d_certified_devices-7.523.dist-info/top_level.txt
z4d_certified_devices-7.523.dist-info/zip-safe
z4d_certified_devices-7.523.dist-info/RECORD
