Metadata-Version: 2.4
Name: z4d-certified-devices
Version: 7.523
Summary: "Certified devices for Zigbee for Domoticz plugin"
Home-page: https://github.com/zigbeefordomoticz/z4d-certified-devices
Author: "Patrick Pichon"
Author-email: "patrick@pichon.me"
License: "GPL-3.0"
Classifier: Programming Language :: Python :: 3
License-File: LICENSE.txt
Dynamic: license-file
